README.md
setup.py
EasyPy2.egg-info/PKG-INFO
EasyPy2.egg-info/SOURCES.txt
EasyPy2.egg-info/dependency_links.txt
EasyPy2.egg-info/requires.txt
EasyPy2.egg-info/top_level.txt
easyweb/__init__.py