Metadata-Version: 2.1
Name: EasyPy2
Version: 0.0.5
Summary: so easy
Home-page: UNKNOWN
Author: Yubadboy
Author-email: 2025677540@qq.com
License: UNKNOWN
Platform: UNKNOWN
